{
  "account": {
    "id": "act_718575088777581",
    "name": "Wholesale Jewelry"
  },
  "meta": {
    "tab": "ecom",
    "media_buyer": "Diana Yaryha",
    "pod_leader": "Diana Yaryha",
    "target_type": "ROAS",
    "target_value": 2.5,
    "budget": 49000,
    "currency": "USD"
  },
  "generated_at": "2026-06-26T16:15:00Z",
  "date_range": {
    "since": "2026-05-27",
    "until": "2026-06-25",
    "label": "Last 30 days (campaign + last-4-weeks rollup)"
  },
  "totals": {
    "total_spend": 41193.42,
    "total_revenue": 233260.63,
    "total_purchases": 767,
    "avg_cpa": 53.71,
    "avg_roas": 5.6626,
    "perf_weeks_used": 4,
    "perf_window": {
      "from": "2026-05-25",
      "to_week_starting": "2026-06-15"
    },
    "ad_count": 0,
    "test_count": 0,
    "test_pct": 0
  },
  "campaigns": [
    {
      "id": "120224989727000594",
      "name": "ASC+ | Campaign | Static",
      "spend": 15884.71
    },
    {
      "id": "120216318340260594",
      "name": "ASC+ | Trends 2026",
      "spend": 11328.57
    },
    {
      "id": "120245983684890594",
      "name": "ASC+ | Body Jewelry Catalog",
      "spend": 3079.65
    },
    {
      "id": "120245989881620594",
      "name": "ASC+ | Summer collection 2026",
      "spend": 2809.6
    },
    {
      "id": "120232531997620594",
      "name": "ASC+ | New arrivals | Reeng and RET",
      "spend": 1962.92
    }
  ],
  "campaign_count_total": 5,
  "campaign_error": null,
  "ads": []
}